[
  {
    "question": "भारतीय संविधान में संशोधन की प्रक्रिया किस अनुच्छेद में दी गई है?",
    "options": ["अनुच्छेद 356", "अनुच्छेद 360", "अनुच्छेद 368", "अनुच्छेद 370"],
    "correctIndex": 2,
    "explanation": "अनुच्छेद 368 संसद को संविधान में संशोधन करने की शक्ति और प्रक्रिया प्रदान करता है।"
  },
  {
    "question": "भारतीय संविधान में 'संवैधानिक संशोधन' की प्रक्रिया किस देश के संविधान से ली गई है?",
    "options": ["संयुक्त राज्य अमेरिका", "दक्षिण अफ्रीका", "कनाडा", "आयरलैंड"],
    "correctIndex": 1,
    "explanation": "भारतीय संविधान में संशोधन की प्रक्रिया दक्षिण अफ्रीका के संविधान से प्रेरित है।"
  },
  {
    "question": "संविधान संशोधन विधेयक संसद के किस सदन में पेश किया जा सकता है?",
    "options": ["केवल लोकसभा", "केवल राज्यसभा", "संसद के किसी भी सदन में", "राज्य विधानसभा में"],
    "correctIndex": 2,
    "explanation": "संविधान संशोधन विधेयक संसद के किसी भी सदन (लोकसभा या राज्यसभा) में पेश किया जा सकता है।"
  },
  {
    "question": "क्या संविधान संशोधन विधेयक के लिए संयुक्त बैठक (Joint Sitting) का प्रावधान है?",
    "options": ["हाँ", "नहीं", "केवल विशेष मामलों में", "राष्ट्रपति की अनुमति पर"],
    "correctIndex": 1,
    "explanation": "संविधान संशोधन विधेयक के लिए संयुक्त बैठक का कोई प्रावधान नहीं है। इसे दोनों सदनों द्वारा अलग-अलग पारित करना अनिवार्य है।"
  },
  {
    "question": "प्रथम संवैधानिक संशोधन अधिनियम, 1951 द्वारा कौन सी अनुसूची जोड़ी गई थी?",
    "options": ["8वीं अनुसूची", "9वीं अनुसूची", "10वीं अनुसूची", "11वीं अनुसूची"],
    "correctIndex": 1,
    "explanation": "प्रथम संविधान संशोधन, 1951 द्वारा 9वीं अनुसूची जोड़ी गई थी, जो मुख्य रूप से भूमि सुधार कानूनों की सुरक्षा से संबंधित है।"
  },
  {
    "question": "किस संविधान संशोधन को 'लघु संविधान' (Mini-Constitution) कहा जाता है?",
    "options": ["42वां संशोधन", "44वां संशोधन", "73वां संशोधन", "86वां संशोधन"],
    "correctIndex": 0,
    "explanation": "42वें संविधान संशोधन (1976) को 'लघु संविधान' कहा जाता है क्योंकि इसमें संविधान में कई व्यापक बदलाव किए गए थे।"
  },
  {
    "question": "42वें संशोधन द्वारा प्रस्तावना में कौन से शब्द जोड़े गए थे?",
    "options": ["समाजवादी, धर्मनिरपेक्ष और अखंडता", "गणतंत्र, लोकतांत्रिक और न्याय", "स्वतंत्रता, समानता और बंधुत्व", "न्याय, धर्मनिरपेक्ष और एकता"],
    "correctIndex": 0,
    "explanation": "42वें संशोधन, 1976 द्वारा प्रस्तावना में 'समाजवादी', 'धर्मनिरपेक्ष' और 'अखंडता' शब्द जोड़े गए थे।"
  },
  {
    "question": "किस संवैधानिक संशोधन द्वारा संपत्ति के अधिकार को मौलिक अधिकारों की सूची से हटाकर कानूनी अधिकार बना दिया गया?",
    "options": ["42वां संशोधन", "44वां संशोधन", "38वां संशोधन", "52वां संशोधन"],
    "correctIndex": 1,
    "explanation": "44वें संविधान संशोधन (1978) द्वारा संपत्ति के अधिकार को मौलिक अधिकार (अनुच्छेद 31) से हटाकर कानूनी अधिकार (अनुच्छेद 300A) बना दिया गया।"
  },
  {
    "question": "दलबदल विरोधी कानून (Anti-Defection Law) किस संवैधानिक संशोधन द्वारा जोड़ा गया था?",
    "options": ["51वां संशोधन", "52वां संशोधन", "53वां संशोधन", "54वां संशोधन"],
    "correctIndex": 1,
    "explanation": "52वें संविधान संशोधन, 1985 द्वारा 10वीं अनुसूची जोड़ी गई, जो दलबदल विरोधी कानून से संबंधित है।"
  },
  {
    "question": "किस संशोधन द्वारा मतदान की आयु 21 वर्ष से घटाकर 18 वर्ष कर दी गई?",
    "options": ["60वां संशोधन", "61वां संशोधन", "62वां संशोधन", "63वां संशोधन"],
    "correctIndex": 1,
    "explanation": "61वें संविधान संशोधन अधिनियम, 1988 के द्वारा मतदान की आयु 21 से घटाकर 18 वर्ष कर दी गई थी।"
  },
  {
    "question": "पंचायती राज व्यवस्था को संवैधानिक दर्जा किस संशोधन द्वारा दिया गया?",
    "options": ["71वां संशोधन", "72वां संशोधन", "73वां संशोधन", "74वां संशोधन"],
    "correctIndex": 2,
    "explanation": "73वें संविधान संशोधन अधिनियम, 1992 द्वारा पंचायती राज को संवैधानिक दर्जा दिया गया और 11वीं अनुसूची जोड़ी गई।"
  },
  {
    "question": "नगर पालिकाओं (Municipalities) को संवैधानिक मान्यता किस संशोधन द्वारा दी गई?",
    "options": ["72वां संशोधन", "73वां संशोधन", "74वां संशोधन", "75वां संशोधन"],
    "correctIndex": 2,
    "explanation": "74वें संविधान संशोधन अधिनियम, 1992 द्वारा नगर पालिकाओं को संवैधानिक दर्जा दिया गया और 12वीं अनुसूची जोड़ी गई।"
  },
  {
    "question": "शिक्षा के अधिकार को मौलिक अधिकार बनाने वाला संशोधन कौन सा है?",
    "options": ["84वां संशोधन", "85वां संशोधन", "86वां संशोधन", "87वां संशोधन"],
    "correctIndex": 2,
    "explanation": "86वें संविधान संशोधन, 2002 द्वारा अनुच्छेद 21A जोड़कर शिक्षा के अधिकार को मौलिक अधिकार बनाया गया।"
  },
  {
    "question": "जीएसटी (GST) किस संविधान संशोधन अधिनियम के तहत लागू किया गया?",
    "options": ["99वां संशोधन", "100वां संशोधन", "101वां संशोधन", "102वां संशोधन"],
    "correctIndex": 2,
    "explanation": "101वां संविधान संशोधन अधिनियम, 2016 के द्वारा जीएसटी (वस्तु एवं सेवा कर) लागू किया गया।"
  },
  {
    "question": "राष्ट्रीय पिछड़ा वर्ग आयोग को संवैधानिक दर्जा किस संशोधन द्वारा दिया गया?",
    "options": ["101वां संशोधन", "102वां संशोधन", "103वां संशोधन", "104वां संशोधन"],
    "correctIndex": 1,
    "explanation": "102वें संविधान संशोधन, 2018 द्वारा राष्ट्रीय पिछड़ा वर्ग आयोग को संवैधानिक दर्जा (अनुच्छेद 338B) प्रदान किया गया।"
  },
  {
    "question": "किस संविधान संशोधन द्वारा आर्थिक रूप से कमजोर वर्गों (EWS) के लिए 10% आरक्षण की व्यवस्था की गई?",
    "options": ["102वां संशोधन", "103वां संशोधन", "104वां संशोधन", "105वां संशोधन"],
    "correctIndex": 1,
    "explanation": "103वें संविधान संशोधन, 2019 द्वारा EWS के लिए 10% आरक्षण की व्यवस्था की गई।"
  },
  {
    "question": "किस संवैधानिक संशोधन ने लोकसभा और राज्य विधानसभाओं में एससी और एसटी के लिए आरक्षण को और 10 वर्षों के लिए बढ़ाया?",
    "options": ["103वां संशोधन", "104वां संशोधन", "105वां संशोधन", "106वां संशोधन"],
    "correctIndex": 1,
    "explanation": "104वें संविधान संशोधन, 2020 द्वारा एससी/एसटी के लिए आरक्षण को 10 वर्षों के लिए बढ़ाया गया, लेकिन एंग्लो-इंडियन के नामांकन को समाप्त कर दिया गया।"
  },
  {
    "question": "किस संशोधन द्वारा ओबीसी सूची बनाने के लिए राज्यों की शक्ति को बहाल किया गया?",
    "options": ["103वां संशोधन", "104वां संशोधन", "105वां संशोधन", "106वां संशोधन"],
    "correctIndex": 2,
    "explanation": "105वें संविधान संशोधन, 2021 द्वारा राज्यों को अपनी ओबीसी सूची तैयार करने की शक्ति बहाल की गई।"
  },
  {
    "question": "किस संविधान संशोधन द्वारा सहकारी समितियों को संवैधानिक सुरक्षा दी गई?",
    "options": ["95वां संशोधन", "96वां संशोधन", "97वां संशोधन", "98वां संशोधन"],
    "correctIndex": 2,
    "explanation": "97वें संविधान संशोधन, 2011 द्वारा सहकारी समितियों के गठन और प्रबंधन को संवैधानिक दर्जा दिया गया।"
  },
  {
    "question": "कौन सा संशोधन मौलिक कर्तव्यों (Fundamental Duties) को भारतीय संविधान में शामिल करता है?",
    "options": ["40वां संशोधन", "42वां संशोधन", "44वां संशोधन", "46वां संशोधन"],
    "correctIndex": 1,
    "explanation": "42वें संविधान संशोधन, 1976 द्वारा भाग IV-A और अनुच्छेद 51A के तहत मौलिक कर्तव्यों को शामिल किया गया।"
  },
  {
    "question": "106वें संविधान संशोधन अधिनियम का मुख्य उद्देश्य क्या है?",
    "options": ["जीएसटी को लागू करना", "लोकसभा और राज्य विधानसभाओं में महिलाओं के लिए आरक्षण", "ओबीसी आरक्षण को विनियमित करना", "शिक्षा का अधिकार"],
    "correctIndex": 1,
    "explanation": "106वें संविधान संशोधन अधिनियम, 2023 के द्वारा लोकसभा और राज्य विधानसभाओं में महिलाओं के लिए 33% (एक-तिहाई) सीटों का आरक्षण प्रदान किया गया है।"
  },
  {
    "question": "किस संविधान संशोधन द्वारा सहकारी समितियों (Co-operative Societies) के गठन को मौलिक अधिकार बनाया गया?",
    "options": ["95वां संशोधन", "96वां संशोधन", "97वां संशोधन", "98वां संशोधन"],
    "correctIndex": 2,
    "explanation": "97वें संविधान संशोधन, 2011 द्वारा अनुच्छेद 19(1)(c) में संशोधन कर सहकारी समितियां बनाने को मौलिक अधिकार बनाया गया।"
  },
  {
    "question": "किस संशोधन द्वारा मंत्रिपरिषद का आकार लोकसभा की कुल सदस्य संख्या के 15% तक सीमित कर दिया गया?",
    "options": ["90वां संशोधन", "91वां संशोधन", "92वां संशोधन", "93वां संशोधन"],
    "correctIndex": 1,
    "explanation": "91वें संविधान संशोधन, 2003 द्वारा यह निश्चित किया गया कि मंत्रिपरिषद का आकार लोकसभा की कुल सदस्य संख्या के 15% से अधिक नहीं होगा।"
  },
  {
    "question": "संविधान के किस संशोधन द्वारा 'दल-बदल' के आधार पर अयोग्यता के प्रावधानों को कठोर बनाया गया?",
    "options": ["52वां संशोधन", "91वां संशोधन", "85वां संशोधन", "73वां संशोधन"],
    "correctIndex": 1,
    "explanation": "91वें संविधान संशोधन, 2003 ने दल-बदल विरोधी कानून को और अधिक प्रभावी बनाया, जिसमें दल-बदल के आधार पर अयोग्यता के अपवाद को समाप्त कर दिया गया।"
  },
  {
    "question": "भारत और बांग्लादेश के बीच भूमि सीमा समझौते (Land Boundary Agreement) के लिए कौन सा संशोधन किया गया?",
    "options": ["99वां संशोधन", "100वां संशोधन", "101वां संशोधन", "102वां संशोधन"],
    "correctIndex": 1,
    "explanation": "100वें संविधान संशोधन, 2015 द्वारा भारत और बांग्लादेश के बीच भूमि सीमा समझौता कार्यान्वित किया गया।"
  },
  {
    "question": "किस संविधान संशोधन द्वारा दिल्ली को 'राष्ट्रीय राजधानी क्षेत्र' (NCT) का दर्जा दिया गया?",
    "options": ["67वां संशोधन", "69वां संशोधन", "70वां संशोधन", "71वां संशोधन"],
    "correctIndex": 1,
    "explanation": "69वें संविधान संशोधन अधिनियम, 1991 के तहत दिल्ली को 'राष्ट्रीय राजधानी क्षेत्र' घोषित किया गया और विधानसभा का प्रावधान किया गया।"
  },
  {
    "question": "अनुसूचित जातियों (SC) के लिए एक अलग राष्ट्रीय आयोग की स्थापना किस संशोधन द्वारा की गई?",
    "options": ["87वां संशोधन", "88वां संशोधन", "89वां संशोधन", "90वां संशोधन"],
    "correctIndex": 2,
    "explanation": "89वें संविधान संशोधन, 2003 द्वारा अनुच्छेद 338A जोड़कर राष्ट्रीय अनुसूचित जनजाति आयोग और अनुच्छेद 338 के तहत अनुसूचित जाति आयोग को अलग किया गया।"
  },
  {
    "question": "किस संविधान संशोधन द्वारा आठवीं अनुसूची में बोडो, डोगरी, मैथिली और संथाली भाषाएं जोड़ी गईं?",
    "options": ["90वां संशोधन", "91वां संशोधन", "92वां संशोधन", "93वां संशोधन"],
    "correctIndex": 2,
    "explanation": "92वें संविधान संशोधन, 2003 के द्वारा आठवीं अनुसूची में बोडो, डोगरी, मैथिली और संथाली को शामिल किया गया, जिससे कुल भाषाओं की संख्या 22 हो गई।"
  },
  {
    "question": "किस संशोधन द्वारा निजी शिक्षण संस्थानों में सामाजिक और शैक्षिक रूप से पिछड़े वर्गों के लिए आरक्षण का प्रावधान किया गया?",
    "options": ["92वां संशोधन", "93वां संशोधन", "94वां संशोधन", "95वां संशोधन"],
    "correctIndex": 1,
    "explanation": "93वें संविधान संशोधन, 2005 द्वारा अनुच्छेद 15(5) जोड़ा गया, जो निजी शैक्षणिक संस्थानों में पिछड़े वर्गों के लिए आरक्षण का प्रावधान करता है।"
  },
  {
    "question": "कौन सा संशोधन मौलिक अधिकारों (Fundamental Rights) के संबंध में संसद की संशोधन शक्ति की पुष्टि करता है?",
    "options": ["24वां संशोधन", "25वां संशोधन", "26वां संशोधन", "27वां संशोधन"],
    "correctIndex": 0,
    "explanation": "24वें संविधान संशोधन, 1971 द्वारा स्पष्ट किया गया कि संसद संविधान के किसी भी हिस्से, जिसमें मौलिक अधिकार भी शामिल हैं, में संशोधन कर सकती है।"
  },
  {
    "question": "किस संवैधानिक संशोधन अधिनियम द्वारा सिक्किम को भारतीय संघ का एक पूर्ण राज्य बनाया गया?",
    "options": ["34वां संशोधन", "35वां संशोधन", "36वां संशोधन", "37वां संशोधन"],
    "correctIndex": 2,
    "explanation": "36वें संविधान संशोधन, 1975 के माध्यम से सिक्किम को भारत का पूर्ण राज्य बनाया गया।"
  },
  {
    "question": "किस संविधान संशोधन द्वारा लोकसभा का कार्यकाल 6 वर्ष से घटाकर पुनः 5 वर्ष कर दिया गया?",
    "options": ["42वां संशोधन", "44वां संशोधन", "46वां संशोधन", "48वां संशोधन"],
    "correctIndex": 1,
    "explanation": "44वें संविधान संशोधन, 1978 द्वारा आपातकाल के दौरान 42वें संशोधन द्वारा किए गए परिवर्तनों को उलटते हुए लोकसभा का कार्यकाल पुनः 5 वर्ष किया गया।"
  },
  {
    "question": "न्यायिक समीक्षा की शक्ति को पुनर्जीवित करने वाला संशोधन कौन सा है?",
    "options": ["42वां संशोधन", "43वां संशोधन", "44वां संशोधन", "45वां संशोधन"],
    "correctIndex": 1,
    "explanation": "43वें संविधान संशोधन, 1977 द्वारा न्यायालयों की न्यायिक समीक्षा की उन शक्तियों को बहाल किया गया जिन्हें 42वें संशोधन द्वारा प्रतिबंधित कर दिया गया था।"
  },
  {
    "question": "कौन सा संशोधन 'आपातकाल' (Emergency) की उद्घोषणा के लिए 'आंतरिक अशांति' (Internal Disturbance) को 'सशस्त्र विद्रोह' (Armed Rebellion) से बदलता है?",
    "options": ["42वां संशोधन", "44वां संशोधन", "46वां संशोधन", "48वां संशोधन"],
    "correctIndex": 1,
    "explanation": "44वें संविधान संशोधन, 1978 के द्वारा 'आंतरिक अशांति' शब्द को हटाकर 'सशस्त्र विद्रोह' शब्द को आधार बनाया गया।"
  },
  {
    "question": "किस संविधान संशोधन के द्वारा राष्ट्रपति को मंत्रिपरिषद की सलाह मानने के लिए बाध्य किया गया?",
    "options": ["40वां संशोधन", "42वां संशोधन", "44वां संशोधन", "46वां संशोधन"],
    "correctIndex": 1,
    "explanation": "42वें संविधान संशोधन, 1976 द्वारा राष्ट्रपति को मंत्रिपरिषद की सलाह मानने के लिए बाध्यकारी बना दिया गया।"
  },
  {
    "question": "कौन सा संशोधन 'राज्य के नीति निर्देशक सिद्धांतों' को 'मौलिक अधिकारों' पर प्राथमिकता देता है?",
    "options": ["25वां संशोधन", "42वां संशोधन", "44वां संशोधन", "52वां संशोधन"],
    "correctIndex": 1,
    "explanation": "42वें संविधान संशोधन, 1976 ने नीति निर्देशक सिद्धांतों को अनुच्छेद 14, 19 और 31 के तहत प्राप्त मौलिक अधिकारों पर प्राथमिकता दी।"
  },
  {
    "question": "किस संविधान संशोधन अधिनियम द्वारा सिंधी भाषा को 8वीं अनुसूची में शामिल किया गया?",
    "options": ["15वां संशोधन", "21वां संशोधन", "22वां संशोधन", "23वां संशोधन"],
    "correctIndex": 1,
    "explanation": "21वें संविधान संशोधन, 1967 के द्वारा सिंधी भाषा को 8वीं अनुसूची में 15वीं भाषा के रूप में जोड़ा गया।"
  },
  {
    "question": "किस संशोधन द्वारा अनुच्छेद 352 के तहत 'आपातकाल' की घोषणा को न्यायिक समीक्षा से बाहर करने का प्रयास किया गया था?",
    "options": ["38वां संशोधन", "40वां संशोधन", "42वां संशोधन", "44वां संशोधन"],
    "correctIndex": 0,
    "explanation": "38वें संविधान संशोधन, 1975 द्वारा यह प्रावधान किया गया था कि आपातकाल की घोषणा को किसी भी न्यायालय में चुनौती नहीं दी जा सकती (जिसे बाद में 44वें संशोधन द्वारा हटा दिया गया)।"
  },
  {
    "question": "किस संविधान संशोधन द्वारा 'वन' (Forests) और 'शिक्षा' (Education) को राज्य सूची से समवर्ती सूची में स्थानांतरित किया गया?",
    "options": ["40वां संशोधन", "42वां संशोधन", "44वां संशोधन", "46वां संशोधन"],
    "correctIndex": 1,
    "explanation": "42वें संविधान संशोधन, 1976 द्वारा शिक्षा, वन, वन्यजीवों और पक्षियों का संरक्षण, माप-तौल और न्याय प्रशासन को समवर्ती सूची में डाला गया।"
  },
  {
    "question": "किस संशोधन द्वारा लोकसभा में अनुसूचित जातियों और अनुसूचित जनजातियों के लिए आरक्षण की अवधि को बढ़ाया गया?",
    "options": ["8वां संशोधन", "23वां संशोधन", "45वां संशोधन", "उपर्युक्त सभी"],
    "correctIndex": 3,
    "explanation": "इन सभी संशोधनों (8वां, 23वां, 45वां) ने समय-समय पर एससी/एसटी आरक्षण की अवधि को बढ़ाने का कार्य किया।"
  },
  {
    "question": "किस संविधान संशोधन द्वारा राष्ट्रीय अनुसूचित जनजाति आयोग (NCST) को एक अलग संवैधानिक निकाय बनाया गया?",
    "options": ["86वां संशोधन", "87वां संशोधन", "88वां संशोधन", "89वां संशोधन"],
    "correctIndex": 3,
    "explanation": "89वें संविधान संशोधन, 2003 द्वारा अनुच्छेद 338A जोड़कर राष्ट्रीय अनुसूचित जनजाति आयोग को राष्ट्रीय अनुसूचित जाति आयोग से अलग कर एक स्वतंत्र संवैधानिक निकाय बनाया गया।"
  },
  {
    "question": "वस्तु एवं सेवा कर (GST) लागू करने के लिए कौन सा संविधान संशोधन अधिनियम पारित किया गया था?",
    "options": ["100वां संशोधन", "101वां संशोधन", "102वां संशोधन", "103वां संशोधन"],
    "correctIndex": 1,
    "explanation": "101वां संविधान संशोधन अधिनियम, 2016 के द्वारा भारत में वस्तु एवं सेवा कर (GST) व्यवस्था को लागू किया गया।"
  },
  {
    "question": "दल-बदल विरोधी कानून (Anti-Defection Law) संविधान की किस अनुसूची के तहत आता है?",
    "options": ["8वीं अनुसूची", "9वीं अनुसूची", "10वीं अनुसूची", "11वीं अनुसूची"],
    "correctIndex": 2,
    "explanation": "52वें संविधान संशोधन, 1985 द्वारा 10वीं अनुसूची जोड़ी गई, जो दलबदल के आधार पर अयोग्यता के प्रावधानों से संबंधित है।"
  }
]

  
  
